{"cameraMode":{"drawMode":0,"name":"Shaded","section":"Shading Mode"},"sceneLighting":false,"audioPlay":false,"sceneViewState":{"showFog":true,"showMaterialUpdate":false,"showSkybox":false,"showFlares":true,"showImageEffects":true,"showParticleSystems":true},"in2DMode":false,"pivot":{"x":-0.3727642297744751,"y":0.5737544298171997,"z":0.1138315200805664},"rotation":{"x":-0.011586805805563927,"y":0.9803773164749146,"z":-0.06067393720149994,"w":-0.18722330033779145},"size":1.77200448513031,"orthographic":false}